hpcblast/__init__.py
hpcblast/_version.py
hpcblast/main.py
hpcblast/src.py
hpcblast/utils.py
hpcblast-1.0.2.dist-info/LICENSE
hpcblast-1.0.2.dist-info/METADATA
hpcblast-1.0.2.dist-info/WHEEL
hpcblast-1.0.2.dist-info/entry_points.txt
hpcblast-1.0.2.dist-info/top_level.txt
hpcblast-1.0.2.dist-info/RECORD
