Metadata-Version: 2.1
Name: hpcblast
Version: 1.0.2
Summary: UNKNOWN
Home-page: https://github.com/yodeng/hpc-blast
License: MIT
Platform: UNKNOWN
Requires-Python: >=3.8
Requires-Dist: cython
Requires-Dist: runjob (>=2.10.5)
